archigeo/basic/__init__.py
archigeo/basic/numeric.pyd
archigeo/basic/numeric.pyi
archigeo/basic/geometry/__init__.py
archigeo/basic/geometry/anglegrid.pyd
archigeo/basic/geometry/anglegrid.pyi
archigeo/basic/geometry/arc2d.pyd
archigeo/basic/geometry/arc2d.pyi
archigeo/basic/geometry/arc3d.pyd
archigeo/basic/geometry/arc3d.pyi
archigeo/basic/geometry/arcseries.pyd
archigeo/basic/geometry/arcseries.pyi
archigeo/basic/geometry/circle.pyd
archigeo/basic/geometry/circle.pyi
archigeo/basic/geometry/ellipse.pyd
archigeo/basic/geometry/ellipse.pyi
archigeo/basic/geometry/geomoop.pyd
archigeo/basic/geometry/geomoop.pyi
archigeo/basic/geometry/ivector.pyd
archigeo/basic/geometry/ivector.pyi
archigeo/basic/geometry/lineseg.pyd
archigeo/basic/geometry/lineseg.pyi
archigeo/basic/geometry/perspective.pyd
archigeo/basic/geometry/perspective.pyi
archigeo/basic/geometry/point.pyd
archigeo/basic/geometry/point.pyi
archigeo/basic/geometry/polyline.pyd
archigeo/basic/geometry/polyline.pyi
archigeo/basic/geometry/rect.pyd
archigeo/basic/geometry/rect.pyi
archigeo/basic/geometry/space3d.pyd
archigeo/basic/geometry/space3d.pyi
archigeo/basic/geomutils/__init__.py
archigeo/basic/geomutils/uangle.pyd
archigeo/basic/geomutils/uangle.pyi
archigeo/basic/geomutils/uline.pyd
archigeo/basic/geomutils/uline.pyi
archigeo/basic/geomutils/uplane.pyd
archigeo/basic/geomutils/uplane.pyi
archigeo/basic/geomutils/upoly.pyd
archigeo/basic/geomutils/upoly.pyi
archigeo/basic/geomutils/urelation.pyd
archigeo/basic/geomutils/urelation.pyi
archigeo/basic/geomutils/uvec.pyd
archigeo/basic/geomutils/uvec.pyi
archigeo/compa/fieldgen.pyd
archigeo/compa/fieldgen.pyi
archigeo/compa/plus.pyd
archigeo/compa/plus.pyi
archigeo/extend/pygame_extend.pyd
archigeo/extend/pygame_extend.pyi
archigeo/extend/rhino_extend.pyd
archigeo/extend/rhino_extend.pyi
archigeo-2.2.3.dist-info/licenses/LICENSE
archigeo-2.2.3.dist-info/METADATA
archigeo-2.2.3.dist-info/WHEEL
archigeo-2.2.3.dist-info/top_level.txt
archigeo-2.2.3.dist-info/RECORD
