Metadata-Version: 2.4
Name: archigeo
Version: 2.2.3
Author: FroggyCroak
License: MIT
Classifier: Programming Language :: Python :: 3 :: Only
Classifier: Programming Language :: Python :: 3.9
Classifier: Operating System :: Microsoft :: Windows
Requires-Python: >=3.9, <3.13
License-File: LICENSE
Dynamic: author
Dynamic: classifier
Dynamic: description
Dynamic: description-content-type
Dynamic: license
Dynamic: license-file
Dynamic: requires-python
